onecord/__init__.py
onecord/__main__.py
onecord/abc.py
onecord/activity.py
onecord/appinfo.py
onecord/asset.py
onecord/audit_logs.py
onecord/backoff.py
onecord/bot.py
onecord/channel.py
onecord/client.py
onecord/colour.py
onecord/components.py
onecord/context_managers.py
onecord/embeds.py
onecord/emoji.py
onecord/enums.py
onecord/errors.py
onecord/file.py
onecord/flags.py
onecord/gateway.py
onecord/guild.py
onecord/http.py
onecord/integrations.py
onecord/interactions.py
onecord/invite.py
onecord/iterators.py
onecord/member.py
onecord/mentions.py
onecord/message.py
onecord/mixins.py
onecord/object.py
onecord/oggparse.py
onecord/opus.py
onecord/partial_emoji.py
onecord/permissions.py
onecord/player.py
onecord/py.typed
onecord/raw_models.py
onecord/reaction.py
onecord/role.py
onecord/shard.py
onecord/stage_instance.py
onecord/state.py
onecord/sticker.py
onecord/team.py
onecord/template.py
onecord/threads.py
onecord/user.py
onecord/utils.py
onecord/voice_client.py
onecord/welcome_screen.py
onecord/widget.py
onecord/app/__init__.py
onecord/app/commands.py
onecord/app/context.py
onecord/bin/libopus-0.x64.dll
onecord/bin/libopus-0.x86.dll
onecord/ext/commands/__init__.py
onecord/ext/commands/_types.py
onecord/ext/commands/bot.py
onecord/ext/commands/cog.py
onecord/ext/commands/context.py
onecord/ext/commands/converter.py
onecord/ext/commands/cooldowns.py
onecord/ext/commands/core.py
onecord/ext/commands/errors.py
onecord/ext/commands/flags.py
onecord/ext/commands/help.py
onecord/ext/commands/view.py
onecord/ext/tasks/__init__.py
onecord/types/__init__.py
onecord/types/activity.py
onecord/types/appinfo.py
onecord/types/audit_log.py
onecord/types/channel.py
onecord/types/components.py
onecord/types/embed.py
onecord/types/emoji.py
onecord/types/gateway.py
onecord/types/guild.py
onecord/types/integration.py
onecord/types/interactions.py
onecord/types/invite.py
onecord/types/member.py
onecord/types/message.py
onecord/types/raw_models.py
onecord/types/role.py
OneCord-3.0.0b0.dist-info/LICENSE
OneCord-3.0.0b0.dist-info/METADATA
OneCord-3.0.0b0.dist-info/WHEEL
OneCord-3.0.0b0.dist-info/top_level.txt
OneCord-3.0.0b0.dist-info/RECORD
